Workbook

Sheet Assumptions
A1: Assumptions | B1: Column1
A2: Retail Price | B2: 90
A3: Units Sold (Monthly) | B3: 1000
A4: Fabric Cost | B4: 18
A5: Manufacturing Labor | B5: 12
A6: Shipping & Duties | B6: 5
A7: Packaging | B7: 2
A8: Store Labor Allocation | B8: 8
A9: Corporate Overhead Allocation | B9: 10
A10: Fixed Store Costs (Monthly) | B10: 25000

Sheet Unit Economics
A1: Total Variable Cost per Unit | B1: =SUM(Assumptions!B4:B9) -> 55
A4: Contribution Margin
A5: Revenue per Unit | B5: =Assumptions!B2 -> 90
A6: Variable Cost Per Unit | B6: =B1 -> 55
A7: Contribution Margin | B7: =B5-B6 -> 35
A8: Contribution Margin % | B8: =B7/B5 -> 0.38888889
A10: Monthly Profit
A11: Total Revenue | B11: =Assumptions!B2 *Assumptions!B3 -> 90000
A12: Total Variable Cost | B12: =Assumptions!B3*'Unit Economics'!B6 -> 55000
A13: Contribution Margin | B13: =B11-B12 -> 35000
A14: Operating Profit | B14: =B13-Assumptions!B10 -> 10000
A17: KPI Table
A18: Revenue | B18: Contribution | C18: Operating Margin
A19: =B11 -> 90000 | B19: =B13 -> 35000 | C19: =B14/B11 -> 0.11111111

Sheet Pricing Sensitivity Table
A1: Price | B1: Units Sold | C1: Revenue | D1: Contribution Margin | E1: Operating Profit
A2: 80 | B2: 1200 | C2: =A2*B2 -> 96000 | D2: =C2-(B2*'Unit Economics'!B1) -> 30000 | E2: =D2-Assumptions!B10 -> 5000
A3: 85 | B3: 1100 | C3: =A3*B3 -> 93500 | D3: =C3-(B3*'Unit Economics'!B1) -> 33000 | E3: =D3-Assumptions!B10 -> 8000
A4: 90 | B4: 1000 | C4: =A4*B4 -> 90000 | D4: =C4-(B4*'Unit Economics'!B1) -> 35000 | E4: =D4-Assumptions!B10 -> 10000
A5: 95 | B5: 920 | C5: =A5*B5 -> 87400 | D5: =C5-(B5*'Unit Economics'!B1) -> 36800 | E5: =D5-Assumptions!B10 -> 11800
A6: 100 | B6: 850 | C6: =A6*B6 -> 85000 | D6: =C6-(B6*'Unit Economics'!B1) -> 38250 | E6: =D6-Assumptions!B10 -> 13250

Sheet Markdown Table
A1: Markdown | B1: Units Sold | C1: Price | D1: Revenue
A2: Full Price | B2: 4000 | C2: 90 | D2: =Table3[[#This Row],[Units Sold]]*Table3[[#This Row],[Price]] -> 360000
A3: Markdown | B3: 1000 | C3: 65 | D3: =Table3[[#This Row],[Units Sold]]*Table3[[#This Row],[Price]] -> 65000

Sheet Markdown Scenario
B1: Initial Production | C1: 5000
B2: Sold at Full Price | C2: 4000
B3: Remaining Inventory | C3: 1000
B4: Markdown Price | C4: 65
B9: Full Price Revenue | C9: =C2*Assumptions!B2 -> 360000
B10: Full Price Profit | C10: =C9-(C2*'Unit Economics'!B1) -> 140000
B11: Markdown Revenue | C11: =C3*C4 -> 65000
B12: Markdown Profit | C12: =C11-(C3*'Unit Economics'!B1) -> 10000
B13: Total Revenue | C13: =C9+C11 -> 425000
B14: Total Profit | C14: =C10+C12 -> 150000
B15: Blended Margin | C15: =C14/C13 -> 0.35294118
B17: Inventory Write-Down Loss | C17: =('Unit Economics'!B1-'Markdown Scenario'!C4) *'Markdown Scenario'!C1 -> -50000

Sheet Summary
A1: Assumptions | D1: Price Sensitivty Table
A2: Assumptions | B2: Column1 | D2: Price | E2: Units Sold | F2: Revenue | G2: Contribution Margin | H2: Operating Profit
A3: Retail Price | B3: 90 | D3: 80 | E3: 1200 | F3: 96000 | G3: 30000 | H3: 5000
A4: Units Sold (Monthly) | B4: 1000 | D4: 85 | E4: 1100 | F4: 93500 | G4: 33000 | H4: 8000
A5: Fabric Cost | B5: 18 | D5: 90 | E5: 1000 | F5: 90000 | G5: 35000 | H5: 10000
A6: Manufacturing Labor | B6: 12 | D6: 95 | E6: 920 | F6: 87400 | G6: 36800 | H6: 11800
A7: Shipping & Duties | B7: 5 | D7: 100 | E7: 850 | F7: 85000 | G7: 38250 | H7: 13250
A8: Packaging | B8: 2
A9: Store Labor Allocation | B9: 8 | D9: Cost Shock/ Inflation Sensitivity
A10: Corporate Overhead Allocation | B10: 10 | D10: Fabric Inflation | E10: Fabric Cost | F10: Unit Variable Cost | G10: Contribution Margin | H10: Operating Profit | I10: Operating Margin
A11: Fixed Store Costs (Monthly) | B11: 25000 | D11: 0 | E11: 18 | F11: 55 | G11: 35 | H11: 10 | I11: 0.11111111
D12: 0.08 | E12: 19.08 | F12: 56.08 | G12: 33.92 | H12: 8.92 | I12: 0.099111111
A13: Unit Economics | D13: 0.12 | E13: 19.12 | F13: 56.12 | G13: 33.88 | H13: 8.88 | I13: 0.098666667
A14: Unit Analysis | B14: Column1
A15: Revenue per Unit | B15: 90 | D15: Markdown Analysis
A16: Variable Cost Per Unit | B16: 55 | D16: Markdown Assumptions | E16: Column2
A17: Contribution Margin | B17: 35 | D17: Initial Production (Units) | E17: 5000
A18: Contribution Margin % | B18: 0.38888889 | D18: Sold at Full Price (Units) | E18: 4000
D19: Remaining Inventory (Units) | E19: 1000
A20: Monthly Profit | B20: Column1 | D20: Markdown Price | E20: 65
A21: Total Revenue | B21: 90000
A22: Total Variable Cost | B22: 55000 | D22: Markdown Results | E22: Column1
A23: Contribution Margin | B23: 35000 | D23: Full Price Revenue | E23: 360000
A24: Operating Profit | B24: 10000 | D24: Full Price Profit | E24: 140000
D25: Markdown Revenue | E25: 65000
D26: Markdown Profit | E26: 10000
D27: Total Revenue | E27: 425000
D28: Total Profit | E28: 150000
D29: Blended Margin | E29: 0.35294118
D31: Inventory Write-Down Loss | E31: -50000

Sheet Inflation Sensitivity
B1: Fabric Inflation | C1: Fabric Cost | D1: Unit Variable Cost | E1: Contribution Margin | F1: Operating Profit | G1: Operating Margin
B2: 0 | C2: =Assumptions!B4 -> 18 | D2: ='Unit Economics'!B6 -> 55 | E2: ='Unit Economics'!B7 -> 35 | F2: =E2-(Assumptions!B10/Assumptions!B3) -> 10 | G2: =F2/'Unit Economics'!B5 -> 0.11111111
B3: 0.08 | C3: =Assumptions!B4+(1+B3) -> 19.08 | D3: =SUM(Assumptions!B5:B9)+C3 -> 56.08 | E3: ='Unit Economics'!B5-D3 -> 33.92 | F3: =E3-(Assumptions!B10/Table1[[#This Row],[Column1]]) -> 8.92 | G3: =F3/'Unit Economics'!B5 -> 0.099111111
B4: 0.12 | C4: =Table1[[#This Row],[Column1]] +(1+'Inflation Sensitivity'!B4) -> 19.12 | D4: =SUM(Assumptions!B5:B9)+C4 -> 56.12 | E4: ='Unit Economics'!B5-D4 -> 33.88 | F4: =E4-(Assumptions!B10/Assumptions!B3) -> 8.88 | G4: =F4/'Unit Economics'!B5 -> 0.098666667
